corona_pickit-0.0.13.dist-info/licenses/LICENSE
pickit/connector.py
pickit/handler.py
pickit/settings.py
corona_pickit-0.0.13.dist-info/METADATA
corona_pickit-0.0.13.dist-info/WHEEL
corona_pickit-0.0.13.dist-info/top_level.txt
corona_pickit-0.0.13.dist-info/RECORD
